sendmsg_toclient/__init__.py
sendmsg_toclient/main.py
sendmsg_toclient-0.1.0.dist-info/METADATA
sendmsg_toclient-0.1.0.dist-info/WHEEL
sendmsg_toclient-0.1.0.dist-info/RECORD
