Metadata-Version: 2.1
Name: sendmsg_toclient
Version: 0.1.0
Summary: Этот пакет преднозначен для отправки сообщений на электронною почту
License: https://mit-license.org
Author: marakhd
Author-email: marakin09@mail.ru
Requires-Python: >=3.12,<4.0
Classifier: License :: Other/Proprietary License
Classifier: Programming Language :: Python :: 3
Classifier: Programming Language :: Python :: 3.12
